zenkit/__init__.py
zenkit/_core.py
zenkit/_native.py
zenkit/cutscene_library.py
zenkit/daedalus_script.py
zenkit/daedalus_vm.py
zenkit/font.py
zenkit/logger.py
zenkit/material.py
zenkit/mesh.py
zenkit/model.py
zenkit/model_animation.py
zenkit/model_hierarchy.py
zenkit/model_mesh.py
zenkit/model_script.py
zenkit/morph_mesh.py
zenkit/multi_resolution_mesh.py
zenkit/soft_skin_mesh.py
zenkit/stream.py
zenkit/texture.py
zenkit/vfs.py
zenkit/core/__init__.py
zenkit/core/color.py
zenkit/core/matrix.py
zenkit/core/quat.py
zenkit/core/vector.py
zenkit/daedalus/__init__.py
zenkit/daedalus/base.py
zenkit/daedalus/camera.py
zenkit/daedalus/effect_base.py
zenkit/daedalus/fightai.py
zenkit/daedalus/focus.py
zenkit/daedalus/guildvalues.py
zenkit/daedalus/info.py
zenkit/daedalus/item.py
zenkit/daedalus/item_react.py
zenkit/daedalus/menu.py
zenkit/daedalus/menu_item.py
zenkit/daedalus/mission.py
zenkit/daedalus/music_jingle.py
zenkit/daedalus/music_system.py
zenkit/daedalus/music_theme.py
zenkit/daedalus/npc.py
zenkit/daedalus/particle_effect.py
zenkit/daedalus/particle_effect_emit_key.py
zenkit/daedalus/sound_effect.py
zenkit/daedalus/sound_system.py
zenkit/daedalus/spell_instance.py
zenkit/daedalus/svm.py
zenkit/native/android-arm64.so
zenkit/native/linux-x64.so
zenkit/native/osx-x64.dylib
zenkit/native/win-x64.dll
zenkit/vob/__init__.py
zenkit/vob/cutscene_camera.py
zenkit/vob/light.py
zenkit/vob/misc.py
zenkit/vob/movable_object.py
zenkit/vob/sound.py
zenkit/vob/trigger.py
zenkit/vob/virtual_object.py
zenkit/vob/zone.py
zenkit/world/__init__.py
zenkit/world/bsp_tree.py
zenkit/world/way_net.py
zenkit/world/world.py
zenkit-1.3.0.4.dist-info/METADATA
zenkit-1.3.0.4.dist-info/WHEEL
zenkit-1.3.0.4.dist-info/top_level.txt
zenkit-1.3.0.4.dist-info/RECORD
